tsunami/__init__.py
tsunami/__main__.py
tsunami/_templates/app_template/__init__.py.tpl
tsunami/_templates/app_template/tests.py.tpl
tsunami/_templates/app_template/handlers/__init__.py.tpl
tsunami/_templates/app_template/handlers/main.py.tpl
tsunami/_templates/project_template/.tsunami.tpl
tsunami/_templates/project_template/__init__.py.tpl
tsunami/_templates/project_template/settings.py.tpl
tsunami/_templates/project_template/apps/__init__.py.tpl
tsunami/_templates/project_template/tasks/__init__.py.tpl
tsunami/_templates/test_template/__init__.py.tpl
tsunami/_templates/test_template/v0.py.tpl
tsunami/bin/tsunami.py
tsunami/conf/__init__.py
tsunami/core/__init__.py
tsunami/core/exceptions.py
tsunami/core/handlers.py
tsunami/core/response.py
tsunami/core/routes.py
tsunami/core/tests.py
tsunami/core/decorators/__init__.py
tsunami/core/decorators/api.py
tsunami/core/decorators/design.py
tsunami/core/decorators/routes.py
tsunami/core/mail/__init__.py
tsunami/core/management/__init__.py
tsunami/core/management/base.py
tsunami/core/management/commands/__init__.py
tsunami/core/management/commands/createapp.py
tsunami/core/management/commands/createproj.py
tsunami/core/management/commands/removeapp.py
tsunami/core/management/commands/runapp.py
tsunami/core/management/commands/runtest.py
tsunami/test/__init__.py
tsunami/utils/__init__.py
tsunami/utils/log.py
tsunami/utils/security.py
tsunami/utils/timezone.py
tsunamiweb-2020.10.22.dist-info/LICENSE
tsunamiweb-2020.10.22.dist-info/METADATA
tsunamiweb-2020.10.22.dist-info/WHEEL
tsunamiweb-2020.10.22.dist-info/entry_points.txt
tsunamiweb-2020.10.22.dist-info/top_level.txt
tsunamiweb-2020.10.22.dist-info/RECORD
